pynput/__init__.py
pynput/__main__.py
pygame_pynput-1.0.dist-info/LICENSE
pygame_pynput-1.0.dist-info/METADATA
pygame_pynput-1.0.dist-info/WHEEL
pygame_pynput-1.0.dist-info/top_level.txt
pygame_pynput-1.0.dist-info/RECORD
