Metadata-Version: 2.1
Name: pygame-pynput
Version: 1.0
Summary: Pygame user input module
Author: Kavin Bharathi
Author-email: r.m.kavinbharathi@gmail.com
Requires-Python: >=3.5
License-File: LICENSE
Requires-Dist: pygame (>=2.1.2)
